LICENSE
MANIFEST.in
README.md
setup.cfg
setup.py
caafinder/__init__.py
caafinder/database.py
caafinder/workspace.py
caafinder.egg-info/PKG-INFO
caafinder.egg-info/SOURCES.txt
caafinder.egg-info/dependency_links.txt
caafinder.egg-info/top_level.txt