Metadata-Version: 1.0
Name: caafinder
Version: 1.0.0
Summary: a library for DS CAA Developer
Home-page: https://github.com/Gutier14/CAAFinder
Author: Luca Liu
Author-email: geekluca@qq.com
License: MIT License
Keywords: ds caa
Platform: any
